partialsmiles/__init__.py
partialsmiles/elements.py
partialsmiles/exceptions.py
partialsmiles/kekulize.py
partialsmiles/smiparser.backup.py
partialsmiles/smiparser.py
partialsmiles/valence.py
partialsmiles-2.0.dist-info/LICENSE
partialsmiles-2.0.dist-info/METADATA
partialsmiles-2.0.dist-info/WHEEL
partialsmiles-2.0.dist-info/top_level.txt
partialsmiles-2.0.dist-info/RECORD
