Metadata-Version: 2.2
Name: partialsmiles
Version: 2.0
Summary: A validating SMILES parser with support for partial SMILES
Home-page: https://github.com/baoilleach/partialsmiles
Author: Noel M. O'Boyle
Author-email: baoilleach@gmail.com
License: MIT License
License-File: LICENSE
Dynamic: author
Dynamic: author-email
Dynamic: home-page
Dynamic: license
Dynamic: summary
